proxies_tg_wrapper/__init__.py
proxies_tg_wrapper/api_wrapper.py
proxies_tg_wrapper-1.0.10.dist-info/licenses/LICENSE
proxies_tg_wrapper-1.0.10.dist-info/METADATA
proxies_tg_wrapper-1.0.10.dist-info/WHEEL
proxies_tg_wrapper-1.0.10.dist-info/top_level.txt
proxies_tg_wrapper-1.0.10.dist-info/RECORD
