Metadata-Version: 2.4
Name: proxies-tg-wrapper
Version: 1.0.10
Summary: A package designed to facilitate interaction with the Telegram API, specifically for managing MTProto proxies.
Home-page: https://github.com/Ilia-Abolhasani/proxies-tg-wrapper
Author: Ilia Abolhasani
Author-email: abolhasani.eliya@gmail.com
Classifier: Programming Language :: Python :: 3
Classifier: License :: OSI Approved :: MIT License
Classifier: Operating System :: OS Independent
Requires-Python: >=3.6
License-File: LICENSE
Requires-Dist: python-telegram==0.18.0
Dynamic: author
Dynamic: author-email
Dynamic: classifier
Dynamic: description
Dynamic: description-content-type
Dynamic: home-page
Dynamic: license-file
Dynamic: requires-dist
Dynamic: requires-python
Dynamic: summary
